{
  "unversionedId": "doc5",
  "id": "doc5",
  "title": "Fifth Document",
  "description": "Another one",
  "source": "@site/../docs/exampledoc5.md",
  "sourceDirName": ".",
  "slug": "/doc5",
  "permalink": "/docs/doc5",
  "draft": false,
  "tags": [],
  "version": "current",
  "lastUpdatedBy": "Author",
  "lastUpdatedAt": 1539502055,
  "formattedLastUpdatedAt": "Oct 14, 2018",
  "frontMatter": {
    "id": "doc5",
    "title": "Fifth Document"
  },
  "sidebar": "docs-other",
  "previous": {
    "title": "Other Document",
    "permalink": "/docs/doc4"
  }
}